{
    "sections": [
        {
            "name": "person_section",
            "label": "Person",
            "columns": [
                {
                    "name": "column_OYDa",
                    "fields": [
                        "custom_user_type",
                        "organization",
                        "salutation",
                        "first_name",
                        "last_name"
                    ]
                },
                {
                    "name": "column_HPSx",
                    "fields": [
                        "mobile_no",
                        "email",
                        "gender"
                    ]
                },
                {
                    "name": "column_5CPV",
                    "fields": [
                        "custom_city",
                        "custom_state",
                        "custom_country",
                        "custom_pincode"
                    ]
                }
            ]
        },
        {
            "name": "hotel_section",
            "label": "Hotel",
            "columns": [
                {
                    "name": "column_TdjW",
                    "fields": [
                        "custom_hotel_property",
                        "custom_no_of_nights"
                    ]
                },
                {
                    "name": "column_WdM3",
                    "fields": [
                        "custom_check_in",
                        "custom_check_out"
                    ]
                }
            ]
        },
        {
            "name": "guest_section",
            "label": "Guest",
            "columns": [
                {
                    "name": "column_Eepm",
                    "fields": [
                        "custom_guest"
                    ]
                }
            ]
        },
        {
            "name": "additional_details_section",
            "label": "Additional Details",
            "columns": [
                {
                    "name": "column_NQkF",
                    "fields": [
                        "custom_rates",
                        "custom_remarks"
                    ]
                },
                {
                    "name": "column_w0eS",
                    "fields": [
                        
                    ]
                }
            ]
        }
    ],
    "remove_fields": [
        "territory",
        "website",
        "annual_revenue",
        "no_of_employees",
        "industry"
    ]
}