{
    "sections": [
        {
            "name": "person_section",
            "label": "Person",
            "columns": [
                {
                    "name": "column_OYDa",
                    "fields": [
                        "custom_user_type",
                        "organization",
                        "salutation",
                        "first_name",
                        "last_name"
                    ]
                },
                {
                    "name": "column_HPSx",
                    "fields": [
                        "mobile_no",
                        "email",
                        "gender"
                    ]
                },
                {
                    "name": "column_5CPV",
                    "fields": [
                        "custom_city",
                        "custom_state",
                        "custom_country",
                        "custom_pincode"
                    ]
                }
            ]
        },
        {
            "name": "hotel_section",
            "label": "Hotel",
            "columns": [
                {
                    "name": "column_PoRL",
                    "fields": [
                        "custom_hotel_property",
                        "custom_no_of_nights"
                    ]
                },
                {
                    "name": "column_RdMn",
                    "fields": [
                        "custom_check_in",
                        "custom_check_out"
                    ]
                }
            ]
        },
        {
            "name": "guest_section",
            "label": "Guest",
            "columns": [
                {
                    "name": "column_hSAE",
                    "fields": [
                        "custom_guest",
                        "custom_remarks"
                    ]
                }
            ]
        },
        {
            "name": "additional_details_section",
            "label": "Additional Details",
            "columns": [
                {
                    "name": "column_dvkB",
                    "fields": [
                        "custom_sub_total",
                        "custom_discount_percent",
                        "custom_discount_amount"
                    ]
                },
                {
                    "name": "column_Aclx",
                    "fields": [
                        "custom_taxable_amount",
                        "custom_tax_amount",
                        "custom_rates"
                    ]
                }
            ]
        }
    ],
    "remove_fields": [
        "territory",
        "website",
        "annual_revenue",
        "no_of_employees",
        "industry"
    ]
}